{"Greater Melbourne": {"death rate": 4.8, "male%": 0.49, "unemployment": 6.8, "age": 36, "income": 672, "housing price": 720000, "educated%": 0.5}, "Greater Sydney": {"death rate": 4.8, "male%": 0.49, "unemployment": 6.1, "age": 36, "income": 717, "housing price": 910000, "educated%": 0.51}, "Greater Adelaide": {"death rate": 5.3, "male%": 0.49, "unemployment": 7.8, "age": 39, "income": 614, "housing price": 477000, "educated%": 0.48}, "Australian Capital Territory": {"death rate": 5.2, "male%": 0.49, "unemployment": 4.8, "age": 35, "income": 997, "housing price": 679800, "educated%": 0.55}}